rabbitmq2psqlwrite/__init__.py
rabbitmq2psqlwrite-1.0.3.data/scripts/rabbitmq2psqlwrite
rabbitmq2psqlwrite-1.0.3.dist-info/LICENCE
rabbitmq2psqlwrite-1.0.3.dist-info/METADATA
rabbitmq2psqlwrite-1.0.3.dist-info/WHEEL
rabbitmq2psqlwrite-1.0.3.dist-info/top_level.txt
rabbitmq2psqlwrite-1.0.3.dist-info/RECORD
